densemixer/__init__.py
densemixer/commands.py
densemixer/logging_utils.py
densemixer/patching.py
densemixer/models/__init__.py
densemixer/models/olmoe_custom.py
densemixer/models/qwen2_moe_custom.py
densemixer/models/qwen3_moe_custom.py
densemixer-1.0.1.dist-info/licenses/LICENSE
densemixer-1.0.1.dist-info/METADATA
densemixer-1.0.1.dist-info/WHEEL
densemixer-1.0.1.dist-info/entry_points.txt
densemixer-1.0.1.dist-info/top_level.txt
densemixer-1.0.1.dist-info/RECORD
