Metadata-Version: 2.4
Name: densemixer
Version: 1.0.1
Summary: Enhanced Mixture of Experts implementation with optimized Straight-Through Estimator router
Author-email: Feng Yao <fengyao@ucsd.edu>
License: MIT
Project-URL: Homepage, https://github.com/yaof20/DenseMixer
Project-URL: Bug Tracker, https://github.com/yaof20/DenseMixer/issues
Keywords: transformers,huggingface,moe,qwen3,olmoe,ste,router
Classifier: Programming Language :: Python :: 3
Classifier: License :: OSI Approved :: MIT License
Classifier: Operating System :: OS Independent
Requires-Python: >=3.10
License-File: LICENSE
Requires-Dist: transformers>=4.51.0
Requires-Dist: torch>=2.0.0
Dynamic: license-file
Dynamic: requires-python
